{"8AK3CqNWbFtkBBoc4zg7EQ==":"mbr-1920x1280.jpg","kSTkpRvg67wmjxiXfDcgnQ==":"agrimel-1920x1020.png","r0qWUQIpFd1IGIEPhqzARg==":"mbr-1-1920x1280.jpg","bvrnXknQBfUzFseP9zBqZg==":"mbr-2-1920x1280.jpg","hEkLUdYx3GUKcDNZdNuPBQ==":"mbr-1920x1285.jpg","J2yzuRiwNjYOxEvYf156hg==":"mbr-1920x1278.jpg","hQjMrENLS7DVyjduIPfu4Q==":"mbr-1920x1281.jpg","4jLRWfjN7OSoOczxa3ZXRQ==":"mbr-1920x1254.jpg","dmGRxhc5bQbut1NlCiNFnA==":"mbr-3-1920x1280.jpg","kntDg2vh4yK3mD/rX7JQ+g==":"mbr-4-1920x1280.jpg","0r98AYLGB5I81ls/tbJ++g==":"mbr-4-1920x1280-b-1920x1280.png","TwH1QRHgQ6v1Zf431rxcgQ==":"mbr-4-1920x1280-b-1920x1280.jpg","odg0fgkb+EuZBZt0NiIJaQ==":"mbr-4-1920x1280-b.svg"}